sutree/__init__.py
sutree/display/__init__.py
sutree/display/abtreedisplay.py
sutree/display/bintreedisplay.py
sutree/display/bintreeparser.py
sutree/display/matrixbuffer.py
sutree/display/nonbintreedisplay.py
sutree/display/nonbintreeparser.py
sutree/display/parsingnode.py
sutree/display/valueutil.py
sutree/tree/__init__.py
sutree/tree/abstracttree.py
sutree/tree/avlnode.py
sutree/tree/avltree.py
sutree/tree/binnode.py
sutree/tree/binsearchtree.py
sutree/tree/bintreeiter.py
sutree/tree/traversal/__init__.py
sutree/tree/traversal/binnonrecurtraversal.py
sutree/tree/traversal/binrecurtraversal.py
sutree/tree/traversal/itraversal.py
sutree-0.2.0.dist-info/LICENSE.txt
sutree-0.2.0.dist-info/METADATA
sutree-0.2.0.dist-info/WHEEL
sutree-0.2.0.dist-info/top_level.txt
sutree-0.2.0.dist-info/RECORD
