Metadata-Version: 2.1
Name: sutree
Version: 0.2.0
Summary: Tree data structure library
Home-page: https://github.com/thanhit95/sutree
Author: Thanh Trung Nguyen
Author-email: thanh.it1995@gmail.com
License: 3-Clause BSD License
Download-URL: https://pypi.org/project/sutree
Keywords: tree,binary,avl,bst,display,view,print,visualize,visualization,ascii,console,terminal
Platform: UNKNOWN
